setup.py
optimage/__init__.py
optimage/utils.py
optimage/backends/__init__.py
optimage/backends/base.py
optimage/backends/gifsicle.py
optimage/backends/jpegoptim.py
optimage/backends/jpegtran.py
optimage/backends/optipng.py
optimage/backends/pngcrush.py
optimage/backends/pngnq.py
optimage/backends/pngout.py
optimage/backends/pngquant.py
optimage/contrib/__init__.py
optimage/contrib/django.py
python_optimage.egg-info/PKG-INFO
python_optimage.egg-info/SOURCES.txt
python_optimage.egg-info/dependency_links.txt
python_optimage.egg-info/top_level.txt