Metadata-Version: 1.1
Name: python-optimage
Version: 1.0.0
Summary: Python library to perform (lossless) images optimization using external tools
Home-page: https://github.com/caxap/python-optimage
Author: Maxim Kamenkov
Author-email: mkamenkov@gmail.com
License: MIT
Platform: UNKNOWN
Classifier: Development Status :: 3 - Alpha
Classifier: Framework :: Django
Classifier: Environment :: Web Environment
Classifier: Intended Audience :: Developers
Classifier: License :: OSI Approved :: MIT License
Classifier: Operating System :: OS Independent
Classifier: Programming Language :: Python
Classifier: Topic :: Software Development :: Libraries
